devrules/__init__.py
devrules/cli.py
devrules/config.py
devrules/main.py
devrules/shell.py
devrules/adapters/__init__.py
devrules/adapters/ai/diny.py
devrules/cli_commands/__init__.py
devrules/cli_commands/branch.py
devrules/cli_commands/build_cmd.py
devrules/cli_commands/commit.py
devrules/cli_commands/config_cmd.py
devrules/cli_commands/dashboard.py
devrules/cli_commands/deploy.py
devrules/cli_commands/group.py
devrules/cli_commands/hook_commands.py
devrules/cli_commands/pr.py
devrules/cli_commands/project.py
devrules/cli_commands/rules.py
devrules/cli_commands/prompters/__init__.py
devrules/cli_commands/prompters/example_usage.py
devrules/cli_commands/prompters/factory.py
devrules/cli_commands/prompters/gum_prompter.py
devrules/cli_commands/prompters/test_verification.py
devrules/cli_commands/prompters/typer_prompter.py
devrules/core/__init__.py
devrules/core/deployment_service.py
devrules/core/enum.py
devrules/core/events_engine.py
devrules/core/functional_groups.py
devrules/core/git_service.py
devrules/core/github_service.py
devrules/core/permission_service.py
devrules/core/project_service.py
devrules/core/rules_engine.py
devrules/dtos/__init__.py
devrules/dtos/github.py
devrules/enterprise/__init__.py
devrules/enterprise/builder.py
devrules/enterprise/config.py
devrules/enterprise/crypto.py
devrules/enterprise/integrity.py
devrules/enterprise/__pycache__/__init__.cpython-311.pyc
devrules/enterprise/__pycache__/__init__.cpython-312.pyc
devrules/enterprise/__pycache__/__init__.cpython-313.pyc
devrules/enterprise/__pycache__/__init__.cpython-314.pyc
devrules/enterprise/__pycache__/builder.cpython-311.pyc
devrules/enterprise/__pycache__/builder.cpython-312.pyc
devrules/enterprise/__pycache__/builder.cpython-313.pyc
devrules/enterprise/__pycache__/builder.cpython-314.pyc
devrules/enterprise/__pycache__/config.cpython-311.pyc
devrules/enterprise/__pycache__/config.cpython-312.pyc
devrules/enterprise/__pycache__/config.cpython-313.pyc
devrules-0.1.9.dist-info/licenses/LICENSE
devrules-0.1.9.dist-info/METADATA
devrules-0.1.9.dist-info/WHEEL
devrules-0.1.9.dist-info/entry_points.txt
devrules-0.1.9.dist-info/top_level.txt
devrules-0.1.9.dist-info/RECORD
