Metadata-Version: 2.4
Name: devrules
Version: 0.1.9
Summary: CLI tool for enforcing development guidelines
Author-email: Pedro Iván Fernández González <pedroifgonzalez@gmail.com>
License: Business Source License 1.1
Project-URL: Homepage, https://github.com/pedroifgonzalez/devrules
Project-URL: Documentation, https://pedroifgonzalez.github.io/devrules/
Project-URL: Repository, https://github.com/pedroifgonzalez/devrules
Project-URL: Bug Tracker, https://github.com/pedroifgonzalez/devrules/issues
Project-URL: Changelog, https://pedroifgonzalez.github.io/devrules/overview/changelog/
Keywords: git,development,workflow,branch-naming,commit-validation,pull-request,code-quality,git-hooks,cli,developer-tools
Classifier: Development Status :: 4 - Beta
Classifier: Intended Audience :: Developers
Classifier: Topic :: Software Development :: Version Control :: Git
Classifier: Topic :: Software Development :: Quality Assurance
Classifier: License :: Other/Proprietary License
Classifier: Programming Language :: Python :: 3
Classifier: Programming Language :: Python :: 3.11
Classifier: Programming Language :: Python :: 3.12
Classifier: Operating System :: OS Independent
Classifier: Environment :: Console
Requires-Python: >=3.11
License-File: LICENSE
Requires-Dist: python-jenkins>=1.8.3
Requires-Dist: requests>=2.32.5
Requires-Dist: toml>=0.10.2
Requires-Dist: typer>=0.20.0
Requires-Dist: cryptography>=41.0.0
Requires-Dist: yaspin>=3.4.0
Requires-Dist: typer-di>=0.1.3
Provides-Extra: tui
Requires-Dist: textual<2.0,>=1.0; extra == "tui"
Requires-Dist: plotext<6.0,>=5.0; extra == "tui"
Requires-Dist: rich<14.0,>=13.0; extra == "tui"
Provides-Extra: enterprise
Requires-Dist: build>=1.0.0; extra == "enterprise"
Requires-Dist: twine>=4.0.0; extra == "enterprise"
Provides-Extra: docs
Requires-Dist: mkdocs>=1.5.0; extra == "docs"
Requires-Dist: mkdocs-material>=9.5.0; extra == "docs"
Requires-Dist: mkdocs-awesome-pages-plugin; extra == "docs"
Dynamic: license-file
